<annotation>
	<folder>images</folder>
	<filename>image662.jpg</filename>
	<path>C:\Users\AALY\Desktop\images\image662.jpg</path>
	<source>
		<database>Unknown</database>
	</source>
	<size>
		<width>100</width>
		<height>100</height>
		<depth>3</depth>
	</size>
	<segmented>0</segmented>
	<object>
		<name>uniform</name>
		<pose>Unspecified</pose>
		<truncated>0</truncated>
		<difficult>0</difficult>
		<bndbox>
			<xmin>74</xmin>
			<ymin>44</ymin>
			<xmax>94</xmax>
			<ymax>90</ymax>
		</bndbox>
	</object>
	<object>
		<name>uniform</name>
		<pose>Unspecified</pose>
		<truncated>0</truncated>
		<difficult>0</difficult>
		<bndbox>
			<xmin>80</xmin>
			<ymin>27</ymin>
			<xmax>93</xmax>
			<ymax>44</ymax>
		</bndbox>
	</object>
	<object>
		<name>uniform</name>
		<pose>Unspecified</pose>
		<truncated>0</truncated>
		<difficult>0</difficult>
		<bndbox>
			<xmin>59</xmin>
			<ymin>22</ymin>
			<xmax>77</xmax>
			<ymax>46</ymax>
		</bndbox>
	</object>
	<object>
		<name>uniform</name>
		<pose>Unspecified</pose>
		<truncated>0</truncated>
		<difficult>0</difficult>
		<bndbox>
			<xmin>45</xmin>
			<ymin>22</ymin>
			<xmax>59</xmax>
			<ymax>47</ymax>
		</bndbox>
	</object>
	<object>
		<name>uniform</name>
		<pose>Unspecified</pose>
		<truncated>0</truncated>
		<difficult>0</difficult>
		<bndbox>
			<xmin>29</xmin>
			<ymin>18</ymin>
			<xmax>41</xmax>
			<ymax>43</ymax>
		</bndbox>
	</object>
	<object>
		<name>uniform</name>
		<pose>Unspecified</pose>
		<truncated>0</truncated>
		<difficult>0</difficult>
		<bndbox>
			<xmin>10</xmin>
			<ymin>18</ymin>
			<xmax>24</xmax>
			<ymax>44</ymax>
		</bndbox>
	</object>
</annotation>
