<annotation>
	<folder>imagegenerator</folder>
	<filename>legal_0_3556.jpeg</filename>
	<path>C:\Users\Talha\Desktop\imagegenerator\legal_0_3556.jpeg</path>
	<source>
		<database>Unknown</database>
	</source>
	<size>
		<width>166</width>
		<height>304</height>
		<depth>3</depth>
	</size>
	<segmented>0</segmented>
	<object>
		<name>uniform</name>
		<pose>Unspecified</pose>
		<truncated>0</truncated>
		<difficult>0</difficult>
		<bndbox>
			<xmin>56</xmin>
			<ymin>16</ymin>
			<xmax>165</xmax>
			<ymax>276</ymax>
		</bndbox>
	</object>
</annotation>
